[{"id_jugador": 1, "posx": 947.5090168041727, "posy": 54.214202211451195, "radio": 30, "direccion": 7058, "color": "gray", "entidad": 1, "energia": 50, "afiliacion": 50, "entidad_energia": 2, "entidad_afiliacion": 3, "inventario": []}, {"id_jugador": 2, "posx": 824.920950817216, "posy": 288.7996983148651, "radio": 30, "direccion": 3344, "color": "silver", "entidad": 4, "energia": 100, "afiliacion": 50, "entidad_energia": 5, "entidad_afiliacion": 6, "inventario": []}, {"id_jugador": 3, "posx": 291.5734942274108, "posy": 57.246161350597966, "radio": 30, "direccion": 11280, "color": "green", "entidad": 7, "energia": 50, "afiliacion": 100, "entidad_energia": 8, "entidad_afiliacion": 9, "inventario": []}, {"id_jugador": 4, "posx": 797.4387410320876, "posy": 582.1701178120184, "radio": 30, "direccion": 2620, "color": "white", "entidad": 10, "energia": 100, "afiliacion": 0, "entidad_energia": 11, "entidad_afiliacion": 12, "inventario": []}, {"id_jugador": 5, "posx": 971.4746069510207, "posy": 35.53237521676495, "radio": 30, "direccion": 6854, "color": "fuchsia", "entidad": 13, "energia": 0, "afiliacion": 100, "entidad_energia": 14, "entidad_afiliacion": 15, "inventario": []}]